aptrade/.dockerignore
aptrade/__init__.py
aptrade/alembic/README
aptrade/alembic/env.py
aptrade/alembic/script.py.mako
aptrade/alembic/versions/3bed69779f09_added_account_table.py
aptrade/alembic/versions/b8f574f4a22a_add_gappers_table.py
aptrade/alembic/versions/d9cd6777ab1d_added_account_table.py
aptrade/alembic/versions/e33d3d2194fd_added_account_table.py
aptrade/analyzers/__init__.py
aptrade/analyzers/annualreturn.py
aptrade/analyzers/base.py
aptrade/analyzers/calmar.py
aptrade/analyzers/drawdown.py
aptrade/analyzers/eq.py
aptrade/analyzers/gapper.py
aptrade/analyzers/leverage.py
aptrade/analyzers/logreturnsrolling.py
aptrade/analyzers/periodstats.py
aptrade/analyzers/positions.py
aptrade/analyzers/progress.py
aptrade/analyzers/pyfolio.py
aptrade/analyzers/returns.py
aptrade/analyzers/sharpe.py
aptrade/analyzers/sortino.py
aptrade/analyzers/sqn.py
aptrade/analyzers/timereturn.py
aptrade/analyzers/trade_history.py
aptrade/analyzers/tradeanalyzer.py
aptrade/analyzers/transactions.py
aptrade/analyzers/vwr.py
aptrade/api/__init__.py
aptrade/api/deps.py
aptrade/api/main.py
aptrade/api/routes/__init__.py
aptrade/api/routes/items.py
aptrade/api/routes/login.py
aptrade/api/routes/private.py
aptrade/api/routes/users.py
aptrade/api/routes/utils.py
aptrade/api_stocks_in_play.py
aptrade/assets/exchanges.csv
aptrade/assets/ticker_info.csv
aptrade/assets/ticker_types.csv
aptrade/backend_pre_start copy.py
aptrade/backend_pre_start.py
aptrade/backtest.py
aptrade/backtrader/__init__.py
aptrade/backtrader/analyzer.py
aptrade/backtrader/analyzers/__init__.py
aptrade/backtrader/analyzers/annualreturn.py
aptrade/backtrader/analyzers/calmar.py
aptrade/backtrader/analyzers/drawdown.py
aptrade/backtrader/analyzers/eq.py
aptrade/backtrader/analyzers/gapper.py
aptrade/backtrader/analyzers/leverage.py
aptrade/backtrader/analyzers/logreturnsrolling.py
aptrade/backtrader/analyzers/periodstats.py
aptrade/backtrader/analyzers/positions.py
aptrade/backtrader/analyzers/progress.py
aptrade-0.2.0.dist-info/WHEEL
aptrade-0.2.0.dist-info/entry_points.txt
aptrade-0.2.0.dist-info/METADATA
aptrade-0.2.0.dist-info/RECORD
