Metadata-Version: 2.3
Name: aptrade
Version: 0.2.0
Summary: Add your description here
Requires-Dist: alembic>=1.17.2
Requires-Dist: backtesting>=0.6.5
Requires-Dist: beautifulsoup4>=4.14.2
Requires-Dist: bn-lightweight-charts>=1.1.0
Requires-Dist: boto3>=1.40.3
Requires-Dist: celery>=5.5.3
Requires-Dist: click>=8.2.1
Requires-Dist: emails>=0.6
Requires-Dist: fastapi-crons>=2.0.1
Requires-Dist: fastapi[standard]
Requires-Dist: ib-async>=2.1.0
Requires-Dist: ipykernel>=6.30.1
Requires-Dist: jwt>=1.4.0
Requires-Dist: massive>=2.0.1
Requires-Dist: matplotlib>=3.10.5
Requires-Dist: mkdocs>=1.6.1
Requires-Dist: mkdocs-material>=9.6.17
Requires-Dist: mkdocstrings-python>=1.17.0
Requires-Dist: mypy>=1.18.2
Requires-Dist: pandas-market-calendars>=5.2.3
Requires-Dist: passlib>=1.7.4
Requires-Dist: plotly>=6.5.1
Requires-Dist: polygon>=1.2.6
Requires-Dist: polygon-api-client>=1.15.3
Requires-Dist: pre-commit>=4.3.0
Requires-Dist: psycopg>=3.2.12
Requires-Dist: psycopg2-binary>=2.9.10
Requires-Dist: pyarrow>=22.0.0
Requires-Dist: pydantic-settings>=2.12.0
Requires-Dist: pyjwt>=2.8.0,<3.0.0
Requires-Dist: pytest>=8.4.1
Requires-Dist: pytest-cov>=6.2.1
Requires-Dist: python-dotenv>=1.1.1
Requires-Dist: python-telegram-bot>=22.5
Requires-Dist: redis>=6.4.0
Requires-Dist: sqlmodel>=0.0.24
Requires-Dist: statsmodels>=0.14.6
Requires-Dist: tenacity>=9.1.2
Requires-Dist: tqdm>=4.67.1
Requires-Dist: uvicorn>=0.35.0
Requires-Python: >=3.12
